test_base_package/__init__.py
test_base_package/cli.py
test_base_package/conftest.py
test_base_package/runner.py
test_base_package/api/__init__.py
test_base_package/api/http_client.py
test_base_package/common/__init__.py
test_base_package/common/plugin.py
test_base_package/template/__init__.py
test_base_package/template/public.py
test_base_package/template/ui.py
test_base_package/ui/__init__.py
test_base_package/ui/base_page.py
test_base_package/ui/build_in_library.py
test_base_package/utils/__init__.py
test_base_package/utils/data.py
test_base_package/utils/logger.py
test_base_package/utils/mysql_util.py
test_base_package/utils/pg_util.py
test_base_package/utils/read_util.py
test_base_package/utils/redis_util.py
test_base_package/utils/sys_util.py
test_base_package/utils/time_util.py
test_base_package-1.0.4.dist-info/METADATA
test_base_package-1.0.4.dist-info/WHEEL
test_base_package-1.0.4.dist-info/entry_points.txt
test_base_package-1.0.4.dist-info/top_level.txt
test_base_package-1.0.4.dist-info/RECORD
